nonebot_plugin_jmdownloader/__init__.py
nonebot_plugin_jmdownloader/config.py
nonebot_plugin_jmdownloader/data_source.py
nonebot_plugin_jmdownloader/utils.py
nonebot_plugin_jmdownloader-1.0.4.dist-info/licenses/LICENSE
nonebot_plugin_jmdownloader-1.0.4.dist-info/METADATA
nonebot_plugin_jmdownloader-1.0.4.dist-info/WHEEL
nonebot_plugin_jmdownloader-1.0.4.dist-info/top_level.txt
nonebot_plugin_jmdownloader-1.0.4.dist-info/RECORD
