Metadata-Version: 2.4
Name: nonebot-plugin-jmdownloader
Version: 1.0.4
Summary: 基于 Nonebot2 的 JMComic 插件
Author-email: Misty02600 <xiao02600@gmail.com>
Project-URL: Repository, https://github.com/Misty02600/nonebot-plugin-jmdownloader
Requires-Python: <4.0,>=3.10
License-File: LICENSE
Requires-Dist: httpx<1.0.0,>=0.27.0
Requires-Dist: nonebot2<3.0.0,>=2.4.2
Requires-Dist: nonebot-plugin-uninfo<1.0.0,>=0.7.0
Requires-Dist: nonebot-plugin-alconna<1.0.0,>=0.56.2
Requires-Dist: nonebot-plugin-waiter<1.0.0,>=0.8.1
Requires-Dist: nonebot-plugin-localstore<1.0.0,>=0.7.4
Requires-Dist: nonebot-plugin-apscheduler<1.0.0,>=0.5.0
Requires-Dist: nonebot-adapter-onebot<3.0.0,>=2.4.6
Requires-Dist: jmcomic>=2.5.35
Requires-Dist: pillow>=11.1.0
Requires-Dist: img2pdf>=0.6.0
Dynamic: license-file
